Metadata-Version: 1.0
Name: factorial-hunan
Version: 0.1
Summary: Factorial Module
Home-page: https://www.baidu.com
Author: Nathan_Hu
Author-email: hunan1217@icloud.com
License: MIT
Platform: Linux
